pymagnetos/__init__.py
pymagnetos/cli.py
pymagnetos/core/__init__.py
pymagnetos/core/_config.py
pymagnetos/core/_data.py
pymagnetos/core/_processor.py
pymagnetos/core/config_models.py
pymagnetos/core/gui/__init__.py
pymagnetos/core/gui/_base_mainwindow.py
pymagnetos/core/gui/widgets/__init__.py
pymagnetos/core/gui/widgets/_batch_processing.py
pymagnetos/core/gui/widgets/_configuration.py
pymagnetos/core/gui/widgets/_files.py
pymagnetos/core/gui/widgets/_graphs.py
pymagnetos/core/gui/widgets/_param_content.py
pymagnetos/core/gui/widgets/_popup_progressbar.py
pymagnetos/core/gui/widgets/_text_logger.py
pymagnetos/core/signal_processing.py
pymagnetos/core/utils.py
pymagnetos/log.py
pymagnetos/py.typed
pymagnetos/pytdo/__init__.py
pymagnetos/pytdo/_config.py
pymagnetos/pytdo/_config_models.py
pymagnetos/pytdo/_tdoprocessor.py
pymagnetos/pytdo/assets/config_default.toml
pymagnetos/pytdo/gui/__init__.py
pymagnetos/pytdo/gui/_worker.py
pymagnetos/pytdo/gui/main.py
pymagnetos/pytdo/gui/widgets/__init__.py
pymagnetos/pytdo/gui/widgets/_buttons.py
pymagnetos/pytdo/gui/widgets/_configuration.py
pymagnetos/pytdo/gui/widgets/_graphs.py
pymagnetos/pytdo/gui/widgets/_param_content.py
pymagnetos/pyuson/__init__.py
pymagnetos/pyuson/_config.py
pymagnetos/pyuson/_config_models.py
pymagnetos/pyuson/_echoprocessor.py
pymagnetos/pyuson/assets/config_default.toml
pymagnetos/pyuson/gui/__init__.py
pymagnetos/pyuson/gui/_worker.py
pymagnetos/pyuson/gui/main.py
pymagnetos/pyuson/gui/widgets/__init__.py
pymagnetos/pyuson/gui/widgets/_buttons.py
pymagnetos/pyuson/gui/widgets/_configuration.py
pymagnetos/pyuson/gui/widgets/_graphs.py
pymagnetos/pyuson/gui/widgets/_param_content.py
pymagnetos-0.1.0.dist-info/WHEEL
pymagnetos-0.1.0.dist-info/entry_points.txt
pymagnetos-0.1.0.dist-info/METADATA
pymagnetos-0.1.0.dist-info/RECORD
