Metadata-Version: 2.3
Name: pymagnetos
Version: 0.1.0
Summary: Applications for high magnetic field analysis
Author: Guillaume Le Goc
Author-email: Guillaume Le Goc <guillaume.le-goc@lncmi.cnrs.fr>
License: MIT
Classifier: Programming Language :: Python :: 3.13
Classifier: Programming Language :: Python :: 3.14
Requires-Dist: fftekwfm>=0.3.0.1
Requires-Dist: matplotlib>=3.10.8
Requires-Dist: nexusformat>=2.0.0
Requires-Dist: numpy>=2.4.1
Requires-Dist: pydantic>=2.12.5
Requires-Dist: pyqt6>=6.10.2
Requires-Dist: pyqtgraph>=0.14.0
Requires-Dist: rich>=14.3.1
Requires-Dist: scipy>=1.17.0
Requires-Dist: tomlkit>=0.14.0
Requires-Python: >=3.13
Project-URL: Source Code, https://gitlab.in2p3.fr/himagnetos/pymagnetos
